snaplayer
