Metadata-Version: 1.1
Name: snaplayer
Version: 0.1.1
Summary: Make images out of your Softlayer virtual servers, painlessly
Home-page: https://github.com/axltxl/snaplayer
Author: Alejandro Ricoveri
Author-email: alejandroricoveri@gmail.com
License: MIT
Download-URL: https://github.com/axltxl/snaplayer/tarball/0.1.1
Keywords: softlayer,backup
Platform: UNKNOWN
Classifier: Development Status :: 3 - Alpha
Classifier: Environment :: Console	
Classifier: Topic :: System :: Archiving :: Backup
Classifier: Natural Language :: English
Classifier: License :: OSI Approved :: MIT License
Classifier: Programming Language :: Python
Classifier: Programming Language :: Python :: 3.5
Classifier: Programming Language :: Python :: 3.4
Classifier: Programming Language :: Python :: 3.3
